{"items":[{"tags":["game-of-thrones","a-song-of-ice-and-fire"],"owner":{"reputation":171,"user_id":15363,"user_type":"registered","profile_image":"https://www.gravatar.com/avatar/5b0cce6c7fbeae9a377d5b1415dd5a52?s=128&d=identicon&r=PG","display_name":"PrisonMonkeys","link":"http://scifi.stackexchange.com/users/15363/prisonmonkeys"},"is_answered":true,"view_count":56,"answer_count":1,"score":3,"last_activity_date":1406296781,"creation_date":1406291784,"question_id":64004,"link":"http://scifi.stackexchange.com/questions/64004/why-did-melisandre-not-die-by-the-poison-in-acok","title":"Why did Melisandre not die by the poison in ACoK?"},{"tags":["george-r-r-martin","a-song-of-ice-and-fire","game-of-thrones"],"owner":{"reputation":2445,"user_id":1522,"user_type":"registered","accept_rate":92,"profile_image":"https://www.gravatar.com/avatar/c597d159d647551b41d4e91f0bcf0dd0?s=128&d=identicon&r=PG","display_name":"riv_rec","link":"http://scifi.stackexchange.com/users/1522/riv-rec"},"is_answered":true,"view_count":27462,"protected_date":1342535970,"accepted_answer_id":2926,"answer_count":18,"score":44,"last_activity_date":1406280808,"creation_date":1303232642,"last_edit_date":1406280808,"question_id":2902,"link":"http://scifi.stackexchange.com/questions/2902/what-plot-differences-are-there-between-the-game-of-thrones-tv-series-and-the-bo","title":"What plot differences are there between the Game of Thrones TV series and the books?"},{"tags":["game-of-thrones","a-song-of-ice-and-fire","george-r-r-martin"],"owner":{"reputation":331,"user_id":25026,"user_type":"registered","profile_image":"https://www.gravatar.com/avatar/bed1a8da1096bc40f94e6fa24642e8f9?s=128&d=identicon&r=PG&f=1","display_name":"Chronicle","link":"http://scifi.stackexchange.com/users/25026/chronicle"},"is_answered":true,"view_count":3163,"accepted_answer_id":54334,"answer_count":2,"score":15,"last_activity_date":1406274753,"creation_date":1397677756,"last_edit_date":1406274753,"question_id":54333,"link":"http://scifi.stackexchange.com/questions/54333/female-bastards-in-game-of-thrones","title":"Female bastards in Game of Thrones"},{"tags":["game-of-thrones","a-song-of-ice-and-fire","george-r-r-martin"],"owner":{"reputation":104,"user_id":27957,"user_type":"unregistered","profile_image":"https://www.gravatar.com/avatar/f6c52bd49a23b802f58256679c77bbf1?s=128&d=identicon&r=PG","display_name":"Kelsey","link":"http://scifi.stackexchange.com/users/27957/kelsey"},"is_answered":true,"view_count":6297,"answer_count":4,"score":20,"last_activity_date":1406274373,"creation_date":1401933781,"last_edit_date":1406274373,"question_id":58644,"link":"http://scifi.stackexchange.com/questions/58644/what-happens-if-both-combatants-die-in-a-trial-by-combat","title":"What happens if both combatants die in a Trial by Combat?"},{"tags":["game-of-thrones","a-song-of-ice-and-fire"],"owner":{"reputation":4752,"user_id":5798,"user_type":"registered","accept_rate":100,"profile_image":"https://www.gravatar.com/avatar/a81805e545b4996b36c7d011a5249b2c?s=128&d=identicon&r=PG","display_name":"Justin Ethier","link":"http://scifi.stackexchange.com/users/5798/justin-ethier"},"is_answered":true,"view_count":146,"accepted_answer_id":63959,"answer_count":1,"score":6,"last_activity_date":1406227010,"creation_date":1406211941,"last_edit_date":1406217692,"question_id":63934,"link":"http://scifi.stackexchange.com/questions/63934/who-secretly-killed-theons-men-in-a-clash-of-kings","title":"Who secretly killed Theon&#39;s men in A Clash of Kings?"},{"tags":["game-of-thrones","a-song-of-ice-and-fire","george-r-r-martin","canon"],"owner":{"reputation":210,"user_id":13663,"user_type":"registered","profile_image":"https://www.gravatar.com/avatar/c92ca12678e1bb6d707186e17a54a1ea?s=128&d=identicon&r=PG&f=1","display_name":"Nicholas","link":"http://scifi.stackexchange.com/users/13663/nicholas"},"is_answered":true,"view_count":714,"accepted_answer_id":59281,"answer_count":3,"score":10,"last_activity_date":1406202971,"creation_date":1402601559,"last_edit_date":1406195706,"question_id":59280,"link":"http://scifi.stackexchange.com/questions/59280/is-there-doubt-that-daenerys-is-aerys-ii-child","title":"Is there doubt that Daenerys is Aerys II child?"},{"tags":["game-of-thrones","a-song-of-ice-and-fire"],"owner":{"reputation":159,"user_id":24620,"user_type":"unregistered","accept_rate":100,"profile_image":"https://www.gravatar.com/avatar/00fd579bf2b460e0f45da7005c0f76a7?s=128&d=identicon&r=PG","display_name":"Lord Snow","link":"http://scifi.stackexchange.com/users/24620/lord-snow"},"is_answered":true,"view_count":194,"accepted_answer_id":63890,"answer_count":1,"score":7,"last_activity_date":1406197229,"creation_date":1406173224,"last_edit_date":1406197229,"question_id":63889,"link":"http://scifi.stackexchange.com/questions/63889/how-well-does-the-wall-work","title":"How well does the Wall work?"},{"tags":["game-of-thrones","a-song-of-ice-and-fire"],"owner":{"reputation":506,"user_id":28409,"user_type":"registered","accept_rate":56,"profile_image":"https://www.gravatar.com/avatar/baca44bd079059229f99de26ff759756?s=128&d=identicon&r=PG","display_name":"dwjohnston","link":"http://scifi.stackexchange.com/users/28409/dwjohnston"},"is_answered":true,"view_count":403,"answer_count":2,"score":6,"last_activity_date":1406172940,"creation_date":1406168534,"last_edit_date":1406169308,"question_id":63885,"link":"http://scifi.stackexchange.com/questions/63885/whats-the-deal-with-illyrio-and-varys","title":"What&#39;s the deal with Illyrio and Varys?"},{"tags":["george-r-r-martin","a-song-of-ice-and-fire","game-of-thrones"],"owner":{"reputation":3344,"user_id":584,"user_type":"registered","accept_rate":53,"profile_image":"https://www.gravatar.com/avatar/1a71658d81f8a82a8122050f21bb86d3?s=128&d=identicon&r=PG","display_name":"Nick T","link":"http://scifi.stackexchange.com/users/584/nick-t"},"is_answered":true,"view_count":10914,"answer_count":4,"score":13,"last_activity_date":1406139625,"creation_date":1333330306,"last_edit_date":1333376311,"question_id":14052,"link":"http://scifi.stackexchange.com/questions/14052/what-does-craster-do-with-his-sons","title":"What does Craster do with his sons?"},{"tags":["game-of-thrones","a-song-of-ice-and-fire"],"owner":{"reputation":4752,"user_id":5798,"user_type":"registered","accept_rate":100,"profile_image":"https://www.gravatar.com/avatar/a81805e545b4996b36c7d011a5249b2c?s=128&d=identicon&r=PG","display_name":"Justin Ethier","link":"http://scifi.stackexchange.com/users/5798/justin-ethier"},"is_answered":true,"view_count":174,"accepted_answer_id":63830,"answer_count":1,"score":2,"last_activity_date":1406127341,"creation_date":1406037394,"last_edit_date":1406056547,"question_id":63775,"link":"http://scifi.stackexchange.com/questions/63775/what-happened-to-rhaegar-frey","title":"What happened to Rhaegar Frey?"}],"has_more":true,"quota_max":300,"quota_remaining":269}
